{
  "tracks" : [
    {
      "id": "1",
      "title": "february 2021",
      "url": "https://storage.googleapis.com/clemsongs/feb2021.mp3",
      "duration": "00:48:42",
      "number": "01",
      "description": "from deepest february. can't remember tracklist",
      "artwork": "https://storage.googleapis.com/clemsongs/55a377af3368e74ad36a0218510f24da.jpeg"
    },
    {
      "id": "2",
      "title": "november 2021",
      "url": "https://storage.googleapis.com/clemsongs/november24.mp3",
      "duration": "00:35:41",
      "number": "02",
      "description": "Félicia Atkinson, Lisa Lerkenfeldt, Susan Howe & David Grubbs, Emacs, Benoit B",
      "artwork": "https://storage.googleapis.com/clemsongs/IMG_7167.jpeg"
    },
    {
      "id": "3",
      "title": "river",
      "url": "https://storage.googleapis.com/clemsongs/river.mp3",
      "duration": "00:19:01",
      "number": "03",
      "description": "Nov 24, 2021. Brian Eno, Marja Ahti, Claire Rousay, Anne-F Jacques, Frank Ocean",
      "artwork": "https://storage.googleapis.com/clemsongs/river.png"
    }
  ]
}